libhung/__init__.py
libhung/hio.py
libhung/hmath.py
libhung/other.py
tests01-0.0.8.dist-info/LICENSE.txt
tests01-0.0.8.dist-info/METADATA
tests01-0.0.8.dist-info/WHEEL
tests01-0.0.8.dist-info/top_level.txt
tests01-0.0.8.dist-info/RECORD
