Metadata-Version: 2.1
Name: tests01
Version: 0.0.8
Summary: basic function
Author: Nguyen Duy Hung
Author-email: hung1410ez@gmail.com
Classifier: Programming Language :: Python :: 3
Classifier: License :: OSI Approved :: MIT License
Classifier: Operating System :: OS Independent
License-File: LICENSE.txt
